geospatialpackage/__init__.py
geospatialpackage/common.py
geospatialpackage/geospatialpackage.py
geospatialpackage-0.0.1.dist-info/LICENSE
geospatialpackage-0.0.1.dist-info/METADATA
geospatialpackage-0.0.1.dist-info/WHEEL
geospatialpackage-0.0.1.dist-info/entry_points.txt
geospatialpackage-0.0.1.dist-info/top_level.txt
geospatialpackage-0.0.1.dist-info/RECORD
