Metadata-Version: 2.2
Name: GeospatialPackage
Version: 0.0.1
Summary: Geospatial package for course
Author-email: Alex McCorkel <amccorketutoring@gmail.com>
License: MIT License
Project-URL: Homepage, https://github.com/amccorketutoring/GeospatialPackage
Keywords: GeospatialPackage
Classifier: Intended Audience :: Developers
Classifier: License :: OSI Approved :: MIT License
Classifier: Natural Language :: English
Classifier: Programming Language :: Python :: 3.8
Classifier: Programming Language :: Python :: 3.9
Classifier: Programming Language :: Python :: 3.10
Classifier: Programming Language :: Python :: 3.11
Classifier: Programming Language :: Python :: 3.12
Requires-Python: >=3.8
License-File: LICENSE
Requires-Dist: numpy
Provides-Extra: all
Requires-Dist: GeospatialPackage[extra]; extra == "all"
Provides-Extra: extra
Requires-Dist: pandas; extra == "extra"
